{"previous_day_tubes": {"no_data": ["wmf12075marv", "wmf12069marv", "wmf12060marv", "wmf12059marv", "wmf12052marv", "wmf12048marv", "wmf12043marv", "wmf12042marv", "wmf12040marv", "wmf12038marv", "wmf12037marv", "wmf12028marv", "wmf12027marv", "wmf12024marv", "wmf12012marv", "wtf13005marv", "wtf13002marv", "wtf11003marv", "wtf11002marv", "wtf10043marv", "wtf10025marv", "wtf10023marv", "wtf10026marv", "wte41002demo", "wmf40145marv", "wmf40013marv", "wmf40009marv", "wmf12088marv", "wmf12103marv", "wmf12023marv", "wte25020marv", "wte25003marv", "mpa27031marv", "wtg03013marv", "wmf40032marv", "wmf40031marv", "wtf21001nemo", "wmf12164marv", "wmf12081marv", "wtf10007marv", "wmf12054marv", "wmf12045marv", "wmf12029marv", "wtf08001marv", "wte46014marv", "wte24006marv", "wte24001marv", "wte19003marv", "mpa27165marv", "mpa27142marv", "mpa27030marv", "wtd29018marv", "wtf10029marv", "wtg03019marv", "wte01009marv", "wmf40149marv", "wmf40006marv", "wmf40003marv", "wmf12022marv", "wmf12013marv", "wtf10041marv", "wte50001marv", "wte25032marv", "wte25016marv", "wte24014marv", "wte19001marv", "mpa27144marv"], "no_vbat": ["wte41002demo", "wmf40013marv", "wmf40009marv", "wmf12103marv", "wte25020marv", "wte25003marv", "mpa27031marv", "wtg03013marv", "wtf21001nemo", "wtf10007marv", "wmf12045marv", "wtf08001marv", "wte24006marv", "wte24001marv", "wte19003marv", "mpa27165marv", "mpa27142marv", "mpa27030marv", "wtd29018marv", "wtg03019marv", "wte01009marv", "wmf40149marv", "wmf40006marv", "wmf40003marv", "wmf12022marv", "wmf12013marv", "wtf10041marv", "wte50001marv", "wte25032marv", "wte25016marv", "wte24014marv", "wte19001marv"], "vbat_low": ["wmf12040marv", "wte25024marv", "mpa27141marv", "mpa27091marv", "mpa27058marv", "mpa27045marv", "mpa27028marv", "mpa27017marv", "wte01010marv", "wtg03017marv", "wte25028marv", "wtd44009marv", "mpa27144marv"], "charged": [], "no_humidity": ["wtg03013marv", "wmf40140marv", "wmf40027marv", "wtf21001nemo", "wtf10007marv", "wmf12045marv", "wtf08001marv", "wte24006marv", "wte24001marv", "wte19003marv", "mpa27165marv", "mpa27142marv", "mpa27030marv"], "humidity_60_to_70": [], "humidity_70_to_80": [], "humidity_80_plus": [], "tenure": {"no_data": {"wmf12075marv": 3, "wmf12069marv": 31, "wmf12060marv": 31, "wmf12059marv": 31, "wmf12052marv": 31, "wmf12048marv": 3, "wmf12043marv": 31, "wmf12042marv": 31, "wmf12040marv": 31, "wmf12038marv": 3, "wmf12037marv": 31, "wmf12028marv": 3, "wmf12027marv": 14, "wmf12024marv": 3, "wmf12012marv": 3, "wtf13005marv": 3, "wtf13002marv": 31, "wtf11003marv": 31, "wtf11002marv": 31, "wtf10043marv": 31, "wtf10025marv": 31, "wtf10023marv": 31, "wtf10026marv": 31, "wte41002demo": 31, "wmf40145marv": 5, "wmf40013marv": 31, "wmf40009marv": 31, "wmf12088marv": 1, "wmf12103marv": 31, "wmf12023marv": 31, "wte25020marv": 31, "wte25003marv": 31, "mpa27031marv": 31, "wtg03013marv": 17, "wmf40032marv": 1, "wmf40031marv": 1, "wtf21001nemo": 30, "wmf12164marv": 1, "wmf12081marv": 5, "wtf10007marv": 31, "wmf12054marv": 31, "wmf12045marv": 31, "wmf12029marv": 1, "wtf08001marv": 2, "wte46014marv": 2, "wte24006marv": 31, "wte24001marv": 31, "wte19003marv": 25, "mpa27165marv": 31, "mpa27142marv": 7, "mpa27030marv": 31, "wtd29018marv": 31, "wtf10029marv": 31, "wtg03019marv": 31, "wte01009marv": 30, "wmf40149marv": 21, "wmf40006marv": 22, "wmf40003marv": 22, "wmf12022marv": 22, "wmf12013marv": 31, "wtf10041marv": 21, "wte50001marv": 21, "wte25032marv": 20, "wte25016marv": 21, "wte24014marv": 21, "wte19001marv": 21, "mpa27144marv": 31}, "no_vbat": {"wte41002demo": 31, "wmf40013marv": 31, "wmf40009marv": 31, "wmf12103marv": 31, "wte25020marv": 31, "wte25003marv": 31, "mpa27031marv": 31, "wtg03013marv": 17, "wtf21001nemo": 30, "wtf10007marv": 31, "wmf12045marv": 31, "wtf08001marv": 2, "wte24006marv": 30, "wte24001marv": 31, "wte19003marv": 15, "mpa27165marv": 31, "mpa27142marv": 7, "mpa27030marv": 31, "wtd29018marv": 31, "wtg03019marv": 31, "wte01009marv": 30, "wmf40149marv": 21, "wmf40006marv": 22, "wmf40003marv": 22, "wmf12022marv": 22, "wmf12013marv": 31, "wtf10041marv": 21, "wte50001marv": 21, "wte25032marv": 20, "wte25016marv": 21, "wte24014marv": 21, "wte19001marv": 21}, "vbat_low": {"wmf12040marv": 16, "wte25024marv": 31, "mpa27141marv": 7, "mpa27091marv": 22, "mpa27058marv": 4, "mpa27045marv": 8, "mpa27028marv": 4, "mpa27017marv": 4, "wte01010marv": 1, "wtg03017marv": 7, "wte25028marv": 2, "wtd44009marv": 16, "mpa27144marv": 9}, "charged": {}, "no_humidity": {"wtg03013marv": 17, "wmf40140marv": 31, "wmf40027marv": 30, "wtf21001nemo": 31, "wtf10007marv": 31, "wmf12045marv": 31, "wtf08001marv": 2, "wte24006marv": 30, "wte24001marv": 31, "wte19003marv": 15, "mpa27165marv": 31, "mpa27142marv": 7, "mpa27030marv": 31}, "humidity_60_to_70": {}, "humidity_70_to_80": {}, "humidity_80_plus": {}}}}